LICENSE.txt
README.md
setup.cfg
setup.py
calmodule/CalFunc.py
calmodule/__init__.py
calmodule.egg-info/PKG-INFO
calmodule.egg-info/SOURCES.txt
calmodule.egg-info/dependency_links.txt
calmodule.egg-info/requires.txt
calmodule.egg-info/top_level.txt