Metadata-Version: 2.1
Name: calmodule
Version: 0.0.1
Summary: testing pypi package deployment
Home-page: https://github.com/sirreajohn/CalModule
Download-URL: https://github.com/sirreajohn/CalModule/archive/refs/tags/0.0.1.tar.gz
Author: sirrea
Author-email: mahesh.patapali@gmail.com
License: MIT
Keywords: test,calculator,asd
Classifier: Development Status :: 3 - Alpha
Classifier: Intended Audience :: Developers
Classifier: Topic :: Software Development :: Build Tools
Classifier: License :: OSI Approved :: MIT License
Classifier: Programming Language :: Python :: 3
Classifier: Programming Language :: Python :: 3.4
Classifier: Programming Language :: Python :: 3.5
Classifier: Programming Language :: Python :: 3.6
Classifier: Programming Language :: Python :: 3.7
Classifier: Programming Language :: Python :: 3.8
Classifier: Programming Language :: Python :: 3.9
Classifier: Programming Language :: Python :: 3.10
Classifier: Programming Language :: Python :: 3.11
License-File: LICENSE.txt
